{
  "schemaVersion": 1,
  "id": "healthindicators",
  "version": "${version}",

  "name": "Health Indicators",
  "description": "Displays a health bar above mobs and players",
  "authors": [
    "AdyTech99"
  ],

  "license": "MIT",
  "icon": "assets/healthindicators/icon.png",

  "environment": "client",
  "entrypoints": {
    "client": [
      "io.github.adytech99.healthindicators.HealthIndicatorsMod"
    ],
    "modmenu" : ["io.github.adytech99.healthindicators.config.ModMenuAPIImpl"]
  },
  "mixins": [
    "healthindicators.mixins.json"
  ],

  "depends": {
    "fabricloader": ">=0.15.9",
    "fabric": "*",
    "minecraft": ">=1.20.5",
    "java": ">=21"
  }
}
